wiliot_tools/__init__.py
wiliot_tools/requirements.txt
wiliot_tools/requirements_dev.txt
wiliot_tools/version.py
wiliot_tools/analyze_packet_data/__init__.py
wiliot_tools/analyze_packet_data/analyze_packet_data.bat
wiliot_tools/analyze_packet_data/analyze_packet_data.py
wiliot_tools/association_tool/__init__.py
wiliot_tools/association_tool/association_configs.py
wiliot_tools/association_tool/association_tool.py
wiliot_tools/association_tool/send_association_to_cloud.py
wiliot_tools/association_tool/manual_tools/__init__.py
wiliot_tools/association_tool/manual_tools/associate_by_file.py
wiliot_tools/association_tool/manual_tools/run_associate_by_file.bat
wiliot_tools/association_tool/sensor_count/__init__.py
wiliot_tools/association_tool/sensor_count/sensor_count.ino
wiliot_tools/local_gateway_gui/__init__.py
wiliot_tools/local_gateway_gui/gateway_gui_resolver.py
wiliot_tools/local_gateway_gui/local_gateway_gui.bat
wiliot_tools/local_gateway_gui/local_gateway_gui.py
wiliot_tools/local_gateway_gui/utils/.gwCommands.json
wiliot_tools/local_gateway_gui/utils/__init__.py
wiliot_tools/local_gateway_gui/utils/advanced_gui.ui
wiliot_tools/local_gateway_gui/utils/configs.gif
wiliot_tools/local_gateway_gui/utils/custom_ep.ui
wiliot_tools/local_gateway_gui/utils/custom_plots.ui
wiliot_tools/local_gateway_gui/utils/debug_mode.py
wiliot_tools/local_gateway_gui/utils/folder.png
wiliot_tools/local_gateway_gui/utils/gw_debugger.ui
wiliot_tools/local_gateway_gui/utils/gw_macros.py
wiliot_tools/owner_change_gui/__init__.py
wiliot_tools/owner_change_gui/internal_functions.py
wiliot_tools/owner_change_gui/owner_change_app.py
wiliot_tools/owner_change_gui/owner_change_gui.bat
wiliot_tools/owner_change_gui/owner_change_main.py
wiliot_tools/owner_change_gui/owner_change_requests_page.py
wiliot_tools/owner_change_gui/owner_change_utils.py
wiliot_tools/owner_change_gui/requests_details_page.py
wiliot_tools/owner_change_gui/send_request_multiple_reels_page.py
wiliot_tools-4.13.0.dist-info/LICENSE
wiliot_tools-4.13.0.dist-info/METADATA
wiliot_tools-4.13.0.dist-info/WHEEL
wiliot_tools-4.13.0.dist-info/top_level.txt
wiliot_tools-4.13.0.dist-info/RECORD
