Metadata-Version: 2.1
Name: wiliot_tools
Version: 4.13.0
Summary: A library for interacting with Wiliot's private tools
Home-page: 
Author: Wiliot
Author-email: support@wiliot.com
License: MIT
Project-URL: Bug Tracker, https://WILIOT-ZENDESK-URL
Classifier: Programming Language :: Python :: 3
Classifier: License :: OSI Approved :: MIT License
Classifier: Operating System :: OS Independent
Requires-Python: >=3.6
License-File: LICENSE
Requires-Dist: setuptools-scm
Requires-Dist: matplotlib
Requires-Dist: pygubu (==0.36.3)
Requires-Dist: customtkinter (>=5.0.3)
Requires-Dist: pillow (>=9.0.1)
Requires-Dist: CtkMessagebox
Requires-Dist: ttkbootstrap (==1.10.1)
Requires-Dist: yoctopuce
Requires-Dist: zebra
Requires-Dist: wiliot-api (>=4.10.15)
Requires-Dist: wiliot-core (>=5.13.1)
